<?xml version="1.0" encoding="UTF-8"?>
<store-state>
    <update-time>2012-03-13T19:07:21</update-time>
    <product id="138">
        <available-quantity>0</available-quantity>
        <maximum-quantity>32</maximum-quantity>
	<name>ESAPACK JUNIOR</name>
    </product>
    <product id="150">
        <available-quantity>13</available-quantity>
        <maximum-quantity>28</maximum-quantity>
	<name>ESAPACK MIDI</name>
    </product>
    <product id="162">
        <available-quantity>13</available-quantity>
        <maximum-quantity>28</maximum-quantity>
	<name>ESAPACK MAXI</name>
    </product>
</store-state>
